ibm_whcs_sdk/__init__.py
ibm_whcs_sdk/common.py
ibm_whcs_sdk/version.py
ibm_whcs_sdk/annotator_for_clinical_data/__init__.py
ibm_whcs_sdk/annotator_for_clinical_data/annotator_for_clinical_data_v1.py
ibm_whcs_sdk/annotator_for_clinical_data/tests/__init__.py
ibm_whcs_sdk/annotator_for_clinical_data/tests/common/__init__.py
ibm_whcs_sdk/annotator_for_clinical_data/tests/common/test_annotation.py
ibm_whcs_sdk/annotator_for_clinical_data/tests/common/test_annotator_output.py
ibm_whcs_sdk/annotator_for_clinical_data/tests/common/test_assistance_annotation.py
ibm_whcs_sdk/annotator_for_clinical_data/tests/common/test_attribute_values.py
ibm_whcs_sdk/annotator_for_clinical_data/tests/common/test_cancer_diagnosis.py
ibm_whcs_sdk/annotator_for_clinical_data/tests/common/test_concept_annotation.py
ibm_whcs_sdk/annotator_for_clinical_data/tests/common/test_concept_value_annotation.py
ibm_whcs_sdk/annotator_for_clinical_data/tests/common/test_disambiguation.py
ibm_whcs_sdk/annotator_for_clinical_data/tests/common/test_ejection_fraction.py
ibm_whcs_sdk/annotator_for_clinical_data/tests/common/test_insight_model.py
ibm_whcs_sdk/annotator_for_clinical_data/tests/common/test_lab_value.py
ibm_whcs_sdk/annotator_for_clinical_data/tests/common/test_medication.py
ibm_whcs_sdk/annotator_for_clinical_data/tests/common/test_negated_span.py
ibm_whcs_sdk/annotator_for_clinical_data/tests/common/test_nlu_entities.py
ibm_whcs_sdk/annotator_for_clinical_data/tests/common/test_procedure.py
ibm_whcs_sdk/annotator_for_clinical_data/tests/common/test_relation.py
ibm_whcs_sdk/annotator_for_clinical_data/tests/common/test_section.py
ibm_whcs_sdk/annotator_for_clinical_data/tests/common/test_smoking.py
ibm_whcs_sdk/annotator_for_clinical_data/tests/common/test_spell_corrected_text.py
ibm_whcs_sdk/annotator_for_clinical_data/tests/common/test_spell_correction.py
ibm_whcs_sdk/annotator_for_clinical_data/tests/common/test_suggestion.py
ibm_whcs_sdk-1.9.0.dist-info/LICENSE.md
ibm_whcs_sdk-1.9.0.dist-info/METADATA
ibm_whcs_sdk-1.9.0.dist-info/WHEEL
ibm_whcs_sdk-1.9.0.dist-info/top_level.txt
ibm_whcs_sdk-1.9.0.dist-info/zip-safe
ibm_whcs_sdk-1.9.0.dist-info/RECORD
