Metadata-Version: 2.1
Name: ibm-whcs-sdk
Version: 1.9.0
Summary: ('This is the Watson Health Cognitive Services Python SDK containing ACD and IML',)
Home-page: https://github.com/IBM/whcs-python-sdk
Author: IBM
Author-email: dcweber@us.ibm.com
License: Apache 2.0
Keywords: PACKAGE_NAME
Platform: UNKNOWN
Classifier: Programming Language :: Python
Classifier: Programming Language :: Python :: 3
Classifier: Programming Language :: Python :: 3.5
Classifier: Programming Language :: Python :: 3.6
Classifier: Programming Language :: Python :: 3.7
Classifier: Programming Language :: Python :: 3.8
Classifier: Development Status :: 4 - Beta
Classifier: Intended Audience :: Developers
Classifier: License :: OSI Approved :: Apache Software License
Classifier: Operating System :: OS Independent
Classifier: Topic :: Software Development :: Libraries :: Python Modules
Classifier: Topic :: Software Development :: Libraries :: Application Frameworks
